selective_linter/__init__.py
selective_linter/__main__.py
selective_linter/git_diff.py
selective_linter/installer.py
selective_linter/linter.py
selective_linter/output.py
selective_linter/selective_linter.py
selective_linter-1.0.1.dist-info/LICENSE
selective_linter-1.0.1.dist-info/METADATA
selective_linter-1.0.1.dist-info/WHEEL
selective_linter-1.0.1.dist-info/entry_points.txt
selective_linter-1.0.1.dist-info/top_level.txt
selective_linter-1.0.1.dist-info/RECORD
