Metadata-Version: 2.1
Name: selective-linter
Version: 1.0.1
Summary: A script to be run from Xcode to lint files as you make changes
Home-page: https://github.com/mattboran/SelectiveSwiftLinter
Author: Matt Boran
Author-email: mattboran@gmail.com
License: UNKNOWN
Download-URL: https://github.com/mattboran/SelectiveSwiftLinter/releases/download/1.0.1/selective_linter-1.0.1-py3-none-any.whl
Platform: UNKNOWN
Classifier: Programming Language :: Python :: 3
Classifier: License :: OSI Approved :: MIT License
Classifier: Operating System :: MacOS :: MacOS X
Requires-Python: >3.0.0
Requires-Dist: sh
